docpipe_ai/__init__.py
docpipe_ai/_batchSizer.py
docpipe_ai/_types.py
docpipe_ai/api/__init__.py
docpipe_ai/api/simple_interface.py
docpipe_ai/cli/__init__.py
docpipe_ai/cli/_pipe.py
docpipe_ai/core/__init__.py
docpipe_ai/core/protocols.py
docpipe_ai/data/__init__.py
docpipe_ai/data/config.py
docpipe_ai/data/content.py
docpipe_ai/data/schemas.py
docpipe_ai/mixins/__init__.py
docpipe_ai/mixins/ai_processing.py
docpipe_ai/mixins/batch_processing.py
docpipe_ai/mixins/caching.py
docpipe_ai/mixins/error_handling.py
docpipe_ai/mixins/structured_output.py
docpipe_ai/mixins/validation.py
docpipe_ai/pipelines/__init__.py
docpipe_ai/pipelines/_base.py
docpipe_ai/pipelines/openai_compat.py
docpipe_ai/processors/__init__.py
docpipe_ai/processors/adaptive_image_processor.py
docpipe_ai/processors/base_processor.py
docpipe_ai/processors/batch_processor.py
docpipe_ai/providers/__init__.py
docpipe_ai/providers/anthropic_provider.py
docpipe_ai/providers/base.py
docpipe_ai/providers/factory.py
docpipe_ai/providers/openai_provider.py
docpipe_ai-0.2.1.dist-info/METADATA
docpipe_ai-0.2.1.dist-info/WHEEL
docpipe_ai-0.2.1.dist-info/entry_points.txt
docpipe_ai-0.2.1.dist-info/RECORD
